[
  {
    "stepName": "checkout_button",
    "tag": "button",
    "id": "checkout",
    "classes": [
      "btn",
      "btn_action",
      "btn_medium",
      "checkout_button",
      ""
    ],
    "text": "Checkout",
    "attributes": {
      "class": "btn btn_action btn_medium checkout_button ",
      "data-test": "checkout",
      "id": "checkout",
      "name": "checkout"
    },
    "timestamp": "2026-03-13T05:37:21.792Z"
  },
  {
    "stepName": "checkout_button",
    "tag": "button",
    "id": "checkout",
    "classes": [
      "btn",
      "btn_action",
      "btn_medium",
      "checkout_button",
      ""
    ],
    "text": "Checkout",
    "attributes": {
      "class": "btn btn_action btn_medium checkout_button ",
      "data-test": "checkout",
      "id": "checkout",
      "name": "checkout"
    },
    "timestamp": "2026-03-13T05:47:46.915Z"
  },
  {
    "stepName": "checkout_button",
    "tag": "button",
    "id": "checkout",
    "classes": [
      "btn",
      "btn_action",
      "btn_medium",
      "checkout_button",
      ""
    ],
    "text": "Checkout",
    "attributes": {
      "class": "btn btn_action btn_medium checkout_button ",
      "data-test": "checkout",
      "id": "checkout",
      "name": "checkout"
    },
    "timestamp": "2026-03-15T02:52:40.609Z"
  },
  {
    "stepName": "checkout_button",
    "tag": "button",
    "id": "checkout",
    "classes": [
      "btn",
      "btn_action",
      "btn_medium",
      "checkout_button",
      ""
    ],
    "text": "Checkout",
    "attributes": {
      "class": "btn btn_action btn_medium checkout_button ",
      "data-test": "checkout",
      "id": "checkout",
      "name": "checkout"
    },
    "timestamp": "2026-03-15T03:06:12.627Z"
  },
  {
    "stepName": "checkout_button",
    "tag": "button",
    "id": "checkout",
    "classes": [
      "btn",
      "btn_action",
      "btn_medium",
      "checkout_button",
      ""
    ],
    "text": "Checkout",
    "attributes": {
      "class": "btn btn_action btn_medium checkout_button ",
      "data-test": "checkout",
      "id": "checkout",
      "name": "checkout"
    },
    "timestamp": "2026-03-15T03:13:33.959Z"
  },
  {
    "stepName": "checkout_button",
    "tag": "button",
    "id": "checkout",
    "classes": [
      "btn",
      "btn_action",
      "btn_medium",
      "checkout_button",
      ""
    ],
    "text": "Checkout",
    "attributes": {
      "class": "btn btn_action btn_medium checkout_button ",
      "data-test": "checkout",
      "id": "checkout",
      "name": "checkout"
    },
    "timestamp": "2026-03-15T03:18:18.246Z"
  },
  {
    "stepName": "checkout_button",
    "tag": "button",
    "id": "checkout",
    "classes": [
      "btn",
      "btn_action",
      "btn_medium",
      "checkout_button",
      ""
    ],
    "text": "Checkout",
    "attributes": {
      "class": "btn btn_action btn_medium checkout_button ",
      "data-test": "checkout",
      "id": "checkout",
      "name": "checkout"
    },
    "timestamp": "2026-03-15T03:22:10.492Z"
  },
  {
    "stepName": "checkout_button",
    "tag": "button",
    "id": "checkout",
    "classes": [
      "btn",
      "btn_action",
      "btn_medium",
      "checkout_button",
      ""
    ],
    "text": "Checkout",
    "attributes": {
      "class": "btn btn_action btn_medium checkout_button ",
      "data-test": "checkout",
      "id": "checkout",
      "name": "checkout"
    },
    "timestamp": "2026-03-15T03:33:38.603Z"
  }
]